viktor_table_view/__init__.py
viktor_table_view/table.html
viktor_table_view/table_view.py
viktor_table_view-0.1.3.dist-info/LICENSE
viktor_table_view-0.1.3.dist-info/METADATA
viktor_table_view-0.1.3.dist-info/WHEEL
viktor_table_view-0.1.3.dist-info/top_level.txt
viktor_table_view-0.1.3.dist-info/RECORD
