Metadata-Version: 2.1
Name: viktor_table_view
Version: 0.1.3
Summary: Table view for VIKTOR applications
Author-email: "S.J. van der Meer" <svandermeer@viktor.ai>
Maintainer-email: "S.J. van der Meer" <svandermeer@viktor.ai>
License: MIT License
Project-URL: Homepage, https://github.com/viktor-platform/viktor_table_view
Project-URL: Bug Reports, https://github.com/viktor-platform/viktor_table_view/issues
Requires-Python: >=3.7
License-File: LICENSE
Requires-Dist: viktor
Requires-Dist: pandas <2.0.0
Provides-Extra: dev
Requires-Dist: black ; extra == 'dev'
Requires-Dist: isort ; extra == 'dev'
Requires-Dist: pylint ; extra == 'dev'
